regridding/__init__.py
regridding/_conservative_ramshaw.py
regridding/_interp_ndarray.py
regridding/_util.py
regridding/geometry.py
regridding/inspect.ipynb
regridding/math.py
regridding/_fill/__init__.py
regridding/_fill/_fill.py
regridding/_fill/_fill_test.py
regridding/_fill/_gauss_seidel.py
regridding/_find_indices/__init__.py
regridding/_find_indices/_find_indices.py
regridding/_find_indices/_find_indices_brute.py
regridding/_find_indices/_find_indices_searchsorted.py
regridding/_find_indices/_tests/__init__.py
regridding/_find_indices/_tests/test_find_indices.py
regridding/_regrid/__init__.py
regridding/_regrid/_regrid.py
regridding/_regrid/_regrid_from_weights.py
regridding/_regrid/_tests/__init__.py
regridding/_regrid/_tests/test_regrid.py
regridding/_weights/__init__.py
regridding/_weights/_weights.py
regridding/_weights/_weights_conservative.py
regridding/_weights/_weights_multilinear.py
regridding/tests/__init__.py
regridding/tests/test_geometry.py
regridding/tests/test_interp_ndarray.py
regridding/tests/test_math.py
regridding-0.2.0.dist-info/METADATA
regridding-0.2.0.dist-info/WHEEL
regridding-0.2.0.dist-info/top_level.txt
regridding-0.2.0.dist-info/RECORD
