Metadata-Version: 2.4
Name: regridding
Version: 0.2.0
Summary: Numba-accelerated interpolation routines
Author-email: "Roy T. Smart" <roytsmart@gmail.com>
Project-URL: Homepage, https://github.com/sun-data/regridding
Project-URL: Documentation, https://regridding.readthedocs.io/en/latest
Classifier: Programming Language :: Python :: 3
Requires-Python: >=3.10
Requires-Dist: numpy
Requires-Dist: numba
Provides-Extra: test
Requires-Dist: pytest; extra == "test"
Requires-Dist: scipy; extra == "test"
Provides-Extra: doc
Requires-Dist: pytest; extra == "doc"
Requires-Dist: scipy; extra == "doc"
Requires-Dist: matplotlib; extra == "doc"
Requires-Dist: graphviz; extra == "doc"
Requires-Dist: sphinx-autodoc-typehints; extra == "doc"
Requires-Dist: sphinxcontrib-bibtex; extra == "doc"
Requires-Dist: pydata-sphinx-theme; extra == "doc"
Requires-Dist: ipykernel; extra == "doc"
Requires-Dist: jupyter-sphinx; extra == "doc"
Requires-Dist: sphinx-favicon; extra == "doc"
Provides-Extra: benchmark
Requires-Dist: asv<=0.6.1; extra == "benchmark"
